{
  "id": "magic_overhaul:ancient_city",
  "color": "#4B0082",
  "enchantments": [
    "minecraft:protection",
    "minecraft:swift_sneak"
  ],
  "blocks": [
    { "block": "minecraft:sculk", "min": 4, "max": 5 },
    { "block": "minecraft:sculk_vein", "min": 4, "max": 5 },
    { "block": "minecraft:sculk_catalyst", "min": 4, "max": 5 },
    { "block": "minecraft:sculk_sensor", "min": 3, "max": 4 },
    { "block": "minecraft:sculk_shrieker", "min": 4, "max": 5 },
    { "block": "minecraft:deepslate", "min": 2, "max": 3 },
    { "block": "minecraft:calcite", "min": 1, "max": 2 },
    { "block": "minecraft:blackstone", "min": 2, "max": 3 },
    { "block": "minecraft:soul_campfire", "min": 1, "max": 2 },
    { "block": "minecraft:soul_fire", "min": 1, "max": 2 },
    { "block": "minecraft:soul_lantern", "min": 1, "max": 2 },
    { "block": "minecraft:soul_torch", "min": 1, "max": 2 },
    { "block": "minecraft:reinforced_deepslate", "min": 200, "max": 1000 }
  ],
  "block_tags": [
    { "tag": "minecraft:wool", "min": 4, "max": 5 },
    { "tag": "minecraft:candles", "min": 4, "max": 5 }
  ],
  "loot": {
    "tables": [
      "minecraft:chests/ancient_city"
    ],
    "chance": 0.5
  },
  "trade": {
    "profession": null,
    "level": 0,
    "max_uses": 0
  }
}
